{"nodes": [{"id": "reference_live_document", "label": "Live Mode Reference (Iteration)", "file_type": "document", "source_file": ".agents/skills/impeccable/reference/live.md", "source_location": null, "source_url": null, "captured_at": null, "author": null, "contributor": null}, {"id": "reference_live_identity_lock", "label": "Identity Lock Concept (Live Mode)", "file_type": "rationale", "source_file": ".agents/skills/impeccable/reference/live.md", "source_location": null, "source_url": null, "captured_at": null, "author": null, "contributor": null}, {"id": "reference_live_carbonize_cleanup", "label": "Carbonize Cleanup Process", "file_type": "rationale", "source_file": ".agents/skills/impeccable/reference/live.md", "source_location": null, "source_url": null, "captured_at": null, "author": null, "contributor": null}, {"id": "reference_live_param_system", "label": "Live Mode Param System (Range/Steps/Toggle)", "file_type": "concept", "source_file": ".agents/skills/impeccable/reference/live.md", "source_location": null, "source_url": null, "captured_at": null, "author": null, "contributor": null}], "edges": [{"source": "reference_live_document", "target": "reference_live_identity_lock", "relation": "references", "confidence": "EXTRACTED", "confidence_score": 1.0, "source_file": ".agents/skills/impeccable/reference/live.md", "source_location": null, "weight": 1.0}, {"source": "reference_live_document", "target": "reference_live_carbonize_cleanup", "relation": "references", "confidence": "EXTRACTED", "confidence_score": 1.0, "source_file": ".agents/skills/impeccable/reference/live.md", "source_location": null, "weight": 1.0}, {"source": "reference_live_document", "target": "reference_live_param_system", "relation": "references", "confidence": "EXTRACTED", "confidence_score": 1.0, "source_file": ".agents/skills/impeccable/reference/live.md", "source_location": null, "weight": 1.0}], "hyperedges": []}